videostream2py/__init__.py
videostream2py/video.py
videostream2py-0.0.2.dist-info/LICENSE
videostream2py-0.0.2.dist-info/METADATA
videostream2py-0.0.2.dist-info/WHEEL
videostream2py-0.0.2.dist-info/top_level.txt
videostream2py-0.0.2.dist-info/RECORD
